{"Tony": {"Account Creation Date": "2020-10-13", "Password": "Tony", "Password Creation Date": "2020-10-13", "FirstName": "Tony", "LastName": "TOny", "Email_Address": "Tony"}, "Bob": {"Account Creation Date": "2020-10-13", "Password": "Bob", "Password Creation Date": "2020-10-13", "FirstName": "Bob", "LastName": "Bob", "Email_Address": "Bob"}, "Zapakh": {"Account Creation Date": "2020-10-24", "Password": "Password", "Password Creation Date": "2020-10-24", "FirstName": "Za", "LastName": "Pakh", "Email_Address": "zapakh@twitch.tv"}}